moodlesg/__init__.py
moodlesg/math/__init__.py
moodlesg/math/base.py
moodlesg/math/constants.py
moodlesg/math/functions/__init__.py
moodlesg/math/functions/common.py
moodlesg/math/functions/compatibility.py
moodlesg/math/functions/extended.py
moodlesg-0.3.1.dist-info/METADATA
moodlesg-0.3.1.dist-info/RECORD
moodlesg-0.3.1.dist-info/WHEEL
moodlesg-0.3.1.dist-info/top_level.txt
