Metadata-Version: 2.1
Name: moodlesg
Version: 0.3.1
Summary: Python package to generate common strings used in moodle for users (not admin level) and manage exported files from moodle and generate files for import.
Home-page: https://github.com/cosmoscalibur/moodlesg
Author: Edward Villegas-Pulgarin
Author-email: cosmoscalibur@gmail.com
License: MIT license
Keywords: moodlesg education moodle
Platform: UNKNOWN
Classifier: Development Status :: 3 - Alpha
Classifier: Intended Audience :: Education
Classifier: License :: OSI Approved :: MIT License
Classifier: Natural Language :: English
Classifier: Programming Language :: Python :: 3
Classifier: Programming Language :: Python :: 3.4
Classifier: Programming Language :: Python :: 3.5
Classifier: Programming Language :: Python :: 3.6
Classifier: Operating System :: OS Independent
Classifier: Topic :: Education
